crypto/modes/gcm_block_cipher.py
crypto/modes/gcm_util.py
crypto/params/AEADParameters.py
crypto/params/__init__.py
sm_bc/__init__.py
sm_bc/crypto/SM2.py
sm_bc/crypto/__init__.py
sm_bc/crypto/cipher.py
sm_bc/crypto/cipher_parameters.py
sm_bc/crypto/digest.py
sm_bc/crypto/extended_digest.py
sm_bc/crypto/sm4.py
sm_bc/crypto/agreement/__init__.py
sm_bc/crypto/agreement/sm2_key_exchange.py
sm_bc/crypto/digests/__init__.py
sm_bc/crypto/digests/general_digest.py
sm_bc/crypto/digests/sm3_digest.py
sm_bc/crypto/engines/__init__.py
sm_bc/crypto/engines/sm2_engine.py
sm_bc/crypto/engines/sm4_engine.py
sm_bc/crypto/kdf/__init__.py
sm_bc/crypto/kdf/kdf.py
sm_bc/crypto/modes/__init__.py
sm_bc/crypto/modes/cbc_block_cipher.py
sm_bc/crypto/modes/cfb_block_cipher.py
sm_bc/crypto/modes/ecb_block_cipher.py
sm_bc/crypto/modes/gcm_block_cipher.py
sm_bc/crypto/modes/ofb_block_cipher.py
sm_bc/crypto/modes/sic_block_cipher.py
sm_bc/crypto/modes/gcm/__init__.py
sm_bc/crypto/modes/gcm/gcm_util.py
sm_bc/crypto/paddings/__init__.py
sm_bc/crypto/paddings/iso10126_padding.py
sm_bc/crypto/paddings/iso7816_4_padding.py
sm_bc/crypto/paddings/padded_buffered_block_cipher.py
sm_bc/crypto/paddings/pkcs7_padding.py
sm_bc/crypto/paddings/zero_byte_padding.py
sm_bc/crypto/params/__init__.py
sm_bc/crypto/params/aead_parameters.py
sm_bc/crypto/params/asymmetric_key_parameter.py
sm_bc/crypto/params/ec_domain_parameters.py
sm_bc/crypto/params/ec_key_parameters.py
sm_bc/crypto/params/ec_private_key_parameters.py
sm_bc/crypto/params/ec_public_key_parameters.py
sm_bc/crypto/params/key_parameter.py
sm_bc/crypto/params/parameters_with_id.py
sm_bc/crypto/params/parameters_with_iv.py
sm_bc/crypto/params/parameters_with_random.py
sm_bc/crypto/params/sm2_key_exchange_private_parameters.py
sm_bc/crypto/params/sm2_key_exchange_public_parameters.py
sm_bc/crypto/signers/__init__.py
sm_bc/crypto/signers/dsa_encoding.py
sm_bc/crypto/signers/dsa_k_calculator.py
sm_bc/crypto/signers/random_dsa_k_calculator.py
sm_py_bc-0.1.9.dist-info/licenses/LICENSE
sm_py_bc-0.1.9.dist-info/METADATA
sm_py_bc-0.1.9.dist-info/WHEEL
sm_py_bc-0.1.9.dist-info/top_level.txt
sm_py_bc-0.1.9.dist-info/RECORD
