Metadata-Version: 2.4
Name: sm-py-bc
Version: 0.1.9
Summary: SM2/SM3/SM4 implementation in Python based on Bouncy Castle
Author-email: Developer <dev@example.com>
License: MIT
Project-URL: Homepage, https://github.com/lihongjie0209/sm-py-bc
Project-URL: Bug Tracker, https://github.com/lihongjie0209/sm-py-bc/issues
Project-URL: Documentation, https://github.com/lihongjie0209/sm-py-bc/tree/master/docs
Project-URL: Source Code, https://github.com/lihongjie0209/sm-py-bc
Keywords: sm2,sm3,sm4,cryptography,chinese-crypto,gm-crypto,bouncy-castle
Classifier: Development Status :: 4 - Beta
Classifier: Intended Audience :: Developers
Classifier: License :: OSI Approved :: MIT License
Classifier: Programming Language :: Python :: 3
Classifier: Programming Language :: Python :: 3.10
Classifier: Programming Language :: Python :: 3.11
Classifier: Programming Language :: Python :: 3.12
Classifier: Topic :: Security :: Cryptography
Classifier: Topic :: Software Development :: Libraries :: Python Modules
Requires-Python: >=3.10
License-File: LICENSE
Provides-Extra: test
Requires-Dist: pytest>=7.0; extra == "test"
Requires-Dist: pytest-cov>=4.0; extra == "test"
Dynamic: license-file
